llmlingua_promptflow/__init__.py
llmlingua_promptflow/tools/__init__.py
llmlingua_promptflow/tools/llmlingua.py
llmlingua_promptflow/tools/utils.py
llmlingua_promptflow/yamls/llmlingua.yaml
tests/__init__.py
tests/test_llmlingua.py
llmlingua_promptflow-0.0.1.dist-info/METADATA
llmlingua_promptflow-0.0.1.dist-info/WHEEL
llmlingua_promptflow-0.0.1.dist-info/entry_points.txt
llmlingua_promptflow-0.0.1.dist-info/top_level.txt
llmlingua_promptflow-0.0.1.dist-info/RECORD
